wolframwebengine/__init__.py
wolframwebengine/__main__.py
wolframwebengine/cli/__init__.py
wolframwebengine/cli/dispatch.py
wolframwebengine/cli/commands/__init__.py
wolframwebengine/cli/commands/benchmark_server.py
wolframwebengine/cli/commands/refactor.py
wolframwebengine/cli/commands/runserver.py
wolframwebengine/cli/commands/test.py
wolframwebengine/examples/__init__.py
wolframwebengine/examples/aiohttp_application.py
wolframwebengine/examples/demo/ask.wl
wolframwebengine/examples/demo/ca.wl
wolframwebengine/examples/demo/form.wl
wolframwebengine/examples/demo/trip.wl
wolframwebengine/examples/djangoapp/__init__.py
wolframwebengine/examples/djangoapp/manage.py
wolframwebengine/examples/djangoapp/urls.py
wolframwebengine/examples/sampleapp/index.wl
wolframwebengine/examples/sampleapp/random.wl
wolframwebengine/examples/sampleapp/some.json
wolframwebengine/examples/sampleapp/some.m
wolframwebengine/examples/sampleapp/some.mx
wolframwebengine/examples/sampleapp/some.wl
wolframwebengine/examples/sampleapp/some.wxf
wolframwebengine/examples/sampleapp/api/index.wl
wolframwebengine/examples/sampleapp/foo/index.wl
wolframwebengine/examples/sampleapp/foo/something.wl
wolframwebengine/examples/sampleapp/foo/bar/index.wl
wolframwebengine/examples/sampleapp/foo/bar/something.wl
wolframwebengine/examples/sampleapp/form/index.wl
wolframwebengine/server/__init__.py
wolframwebengine/server/app.py
wolframwebengine/server/explorer.py
wolframwebengine/tests/__init__.py
wolframwebengine/tests/application_aiohttp.py
wolframwebengine/tests/application_django.py
wolframwebengine/tests/folder_explorer.py
wolframwebengine/web/__init__.py
wolframwebengine/web/aiohttp.py
wolframwebengine/web/django.py
wolframwebengine/web/utils.py
wolframwebengine-1.0.4.dist-info/LICENSE
wolframwebengine-1.0.4.dist-info/METADATA
wolframwebengine-1.0.4.dist-info/WHEEL
wolframwebengine-1.0.4.dist-info/entry_points.txt
wolframwebengine-1.0.4.dist-info/top_level.txt
wolframwebengine-1.0.4.dist-info/RECORD
