Metadata-Version: 2.1
Name: wolframwebengine
Version: 1.0.4
Summary: A Python library with various tools to start a wolfram engine a server content.
Author: Wolfram Research, Riccardo Di Virgilio
Author-email: support@wolfram.com, riccardod@wolfram.com
Project-URL: Source code, https://github.com/WolframResearch/WolframWebEngineForPython
Project-URL: Wolfram Research, https://www.wolfram.com
Keywords: Wolfram Language,Wolfram Desktop,Mathematica,Web Development,Wolfram Web Engine
Classifier: License :: OSI Approved :: MIT License
Classifier: Programming Language :: Python
Classifier: Programming Language :: Python :: 3
Classifier: Programming Language :: Python :: 3.5
Classifier: Programming Language :: Python :: 3.6
Classifier: Programming Language :: Python :: 3.7
Classifier: Topic :: Software Development :: Libraries
Requires-Python: >=3.5.3
License-File: LICENSE
Requires-Dist: wolframclient >=1.1.10
Requires-Dist: aiohttp >=3.5.4
